LICENSE.rst
README.md
setup.cfg
setup.py
ieseg_credscore/OBG.py
ieseg_credscore/WOE.py
ieseg_credscore/__init__.py
ieseg_credscore.egg-info/PKG-INFO
ieseg_credscore.egg-info/SOURCES.txt
ieseg_credscore.egg-info/dependency_links.txt
ieseg_credscore.egg-info/requires.txt
ieseg_credscore.egg-info/top_level.txt