Metadata-Version: 2.1
Name: ieseg-credscore
Version: 0.23.6
Summary: Credit Scoring - IESEG School of Management
Home-page: https://github.com/pnborchert
Author: Philipp Borchert
Author-email: p.borchert@ieseg.fr
License: MIT
Keywords: Credit Scoring IESEG
License-File: LICENSE.rst
